bbopt/__coconut__.py
bbopt/__init__.py
bbopt/__main__.py
bbopt/benchmarking.py
bbopt/cli.py
bbopt/constants.py
bbopt/optimizer.py
bbopt/params.py
bbopt/registry.py
bbopt/util.py
bbopt/backends/__init__.py
bbopt/backends/bandit.py
bbopt/backends/bask.py
bbopt/backends/hyperopt.py
bbopt/backends/mixture.py
bbopt/backends/openai.py
bbopt/backends/pysot.py
bbopt/backends/random.py
bbopt/backends/serving.py
bbopt/backends/skopt.py
bbopt/backends/util.py
bbopt/examples/__init__.py
bbopt/examples/any_fast_example.py
bbopt/examples/bask_example.py
bbopt/examples/conditional_hyperopt_example.py
bbopt/examples/conditional_skopt_example.py
bbopt/examples/hyperopt_example.py
bbopt/examples/json_example.py
bbopt/examples/keras_example.py
bbopt/examples/meta_example.py
bbopt/examples/mixture_example.py
bbopt/examples/numpy_example.py
bbopt/examples/pysot_example.py
bbopt/examples/random_example.py
bbopt/examples/remove_erroring_algs_example.py
bbopt/examples/skopt_example.py
bbopt/examples/tpe_or_gp_example.py
bbopt/tests/__init__.py
bbopt/tests/constants_test.py
bbopt/tests/examples_test.py
bbopt-1.4.2.dist-info/LICENSE
bbopt-1.4.2.dist-info/METADATA
bbopt-1.4.2.dist-info/WHEEL
bbopt-1.4.2.dist-info/entry_points.txt
bbopt-1.4.2.dist-info/top_level.txt
bbopt-1.4.2.dist-info/RECORD
