Metadata-Version: 2.1
Name: bbopt
Version: 1.4.2
Summary: The easiest hyperparameter optimization you'll ever do.
Home-page: https://github.com/evhub/bbopt
Author: Evan Hubinger
Author-email: evanjhub@gmail.com
License: UNKNOWN
Platform: UNKNOWN
Classifier: Development Status :: 5 - Production/Stable
Classifier: License :: OSI Approved :: Apache Software License
Classifier: Topic :: Software Development :: Libraries :: Python Modules
Classifier: Operating System :: OS Independent
License-File: LICENSE
Requires-Dist: numpy (>=1.15.1)
Requires-Dist: matplotlib (>=2.2.5)
Requires-Dist: futures (>=3.3) ; python_version<'3'
Requires-Dist: scikit-learn (>=0.20.4) ; python_version<'3'
Requires-Dist: scikit-optimize (<0.9,>=0.8.1) ; python_version<'3'
Requires-Dist: portalocker (<2.0,>=1.7.1) ; python_version<'3'
Requires-Dist: hyperopt (<0.2,>=0.1.2) ; python_version<'3'
Requires-Dist: networkx (<2.0,>=1.0) ; python_version<'3'
Requires-Dist: pysot (>=0.3.3) ; python_version>='3'
Requires-Dist: portalocker (>=2.2.1) ; python_version>='3'
Requires-Dist: hyperopt (>=0.2.5) ; python_version>='3'
Requires-Dist: scikit-optimize (>=0.8.1) ; python_version>='3'
Requires-Dist: openai (>=0.6.4) ; python_version>='3'
Requires-Dist: scikit-learn (>=0.23.2) ; python_version>='3'
Requires-Dist: networkx (>=2.2) ; python_version>='3'
Requires-Dist: pymongo (>=3.9) ; python_version>='3'
Requires-Dist: pyspark (>=2.4) ; python_version>='3'
Requires-Dist: bask (>=0.10.6) ; python_version>='3.7'
Provides-Extra: dev
Requires-Dist: coconut-develop ; extra == 'dev'
Requires-Dist: pytest (>=3.0) ; extra == 'dev'
Requires-Dist: tensorflow (>=2.0) ; (python_version >= "3") and extra == 'dev'
Provides-Extra: examples
Requires-Dist: tensorflow (>=2.0) ; (python_version >= "3") and extra == 'examples'
